{
	"configurations" : 
	[
		{
			"abstractTargets" : 
			[
				{
					"directoryIndex" : 4,
					"id" : "GLEW::GLEW::@f77c298895aae6dc9943",
					"jsonFile" : "target-GLEW__GLEW-76efd4877540ee905e9c.json",
					"name" : "GLEW::GLEW",
					"projectIndex" : 0
				},
				{
					"directoryIndex" : 4,
					"id" : "GLEW::glew::@f77c298895aae6dc9943",
					"jsonFile" : "target-GLEW__glew-c24a79edcf05960ff36b.json",
					"name" : "GLEW::glew",
					"projectIndex" : 0
				},
				{
					"directoryIndex" : 4,
					"id" : "OpenGL::EGL::@f77c298895aae6dc9943",
					"jsonFile" : "target-OpenGL__EGL-a3fc36401fa2c958457e.json",
					"name" : "OpenGL::EGL",
					"projectIndex" : 0
				},
				{
					"directoryIndex" : 4,
					"id" : "OpenGL::GL::@f77c298895aae6dc9943",
					"jsonFile" : "target-OpenGL__GL-9c44bbeb00da108da759.json",
					"name" : "OpenGL::GL",
					"projectIndex" : 0
				},
				{
					"directoryIndex" : 4,
					"id" : "OpenGL::GLES2::@f77c298895aae6dc9943",
					"jsonFile" : "target-OpenGL__GLES2-2768972146f021fd9f69.json",
					"name" : "OpenGL::GLES2",
					"projectIndex" : 0
				},
				{
					"directoryIndex" : 4,
					"id" : "OpenGL::GLES3::@f77c298895aae6dc9943",
					"jsonFile" : "target-OpenGL__GLES3-1a6f1de2a3374da2ad96.json",
					"name" : "OpenGL::GLES3",
					"projectIndex" : 0
				},
				{
					"directoryIndex" : 4,
					"id" : "OpenGL::GLU::@f77c298895aae6dc9943",
					"jsonFile" : "target-OpenGL__GLU-ca0ac3c29143dfbfe859.json",
					"name" : "OpenGL::GLU",
					"projectIndex" : 0
				},
				{
					"directoryIndex" : 4,
					"id" : "OpenGL::GLX::@f77c298895aae6dc9943",
					"jsonFile" : "target-OpenGL__GLX-0811c8d2a59fabb3e8e0.json",
					"name" : "OpenGL::GLX",
					"projectIndex" : 0
				},
				{
					"directoryIndex" : 4,
					"id" : "OpenGL::OpenGL::@f77c298895aae6dc9943",
					"jsonFile" : "target-OpenGL__OpenGL-3f0ed5d595dfcad8eb7d.json",
					"name" : "OpenGL::OpenGL",
					"projectIndex" : 0
				},
				{
					"directoryIndex" : 4,
					"id" : "Threads::Threads::@f77c298895aae6dc9943",
					"jsonFile" : "target-Threads__Threads-94f5c08bf57df6efe717.json",
					"name" : "Threads::Threads",
					"projectIndex" : 0
				},
				{
					"directoryIndex" : 1,
					"id" : "core::@57760688d1f824db5d9c",
					"jsonFile" : "target-core-305d1460168aae66963a.json",
					"name" : "core",
					"projectIndex" : 0
				},
				{
					"directoryIndex" : 4,
					"id" : "glfw::@f77c298895aae6dc9943",
					"jsonFile" : "target-glfw-9bc501c6fd952048c99c.json",
					"name" : "glfw",
					"projectIndex" : 0
				},
				{
					"directoryIndex" : 4,
					"id" : "graphics::@f77c298895aae6dc9943",
					"jsonFile" : "target-graphics-5d4b228cc0979be6335e.json",
					"name" : "graphics",
					"projectIndex" : 0
				}
			],
			"directories" : 
			[
				{
					"build" : ".",
					"childIndexes" : 
					[
						1,
						7
					],
					"jsonFile" : "directory-.-9ad1a58d4644cf6543fa.json",
					"minimumCMakeVersion" : 
					{
						"string" : "3.12"
					},
					"projectIndex" : 0,
					"source" : "."
				},
				{
					"abstractTargetIndexes" : 
					[
						10
					],
					"build" : "core",
					"childIndexes" : 
					[
						2,
						3,
						4,
						5,
						6
					],
					"jsonFile" : "directory-core-4569dd2465794923f389.json",
					"minimumCMakeVersion" : 
					{
						"string" : "3.12"
					},
					"parentIndex" : 0,
					"projectIndex" : 0,
					"source" : "core"
				},
				{
					"build" : "core/Window",
					"jsonFile" : "directory-core.Window-632de1bd08392c2bf8e8.json",
					"minimumCMakeVersion" : 
					{
						"string" : "3.12"
					},
					"parentIndex" : 1,
					"projectIndex" : 0,
					"source" : "core/Window",
					"targetIndexes" : 
					[
						4
					]
				},
				{
					"build" : "core/Input",
					"jsonFile" : "directory-core.Input-2a3d04195aa5c18bd67a.json",
					"minimumCMakeVersion" : 
					{
						"string" : "3.12"
					},
					"parentIndex" : 1,
					"projectIndex" : 0,
					"source" : "core/Input",
					"targetIndexes" : 
					[
						2
					]
				},
				{
					"abstractTargetIndexes" : 
					[
						0,
						1,
						2,
						3,
						4,
						5,
						6,
						7,
						8,
						9,
						11,
						12
					],
					"build" : "core/Graphics",
					"jsonFile" : "directory-core.Graphics-57e21e6c7b6bb208495f.json",
					"minimumCMakeVersion" : 
					{
						"string" : "3.12"
					},
					"parentIndex" : 1,
					"projectIndex" : 0,
					"source" : "core/Graphics"
				},
				{
					"build" : "core/Game",
					"jsonFile" : "directory-core.Game-b4f213fa62211d29dc3a.json",
					"minimumCMakeVersion" : 
					{
						"string" : "3.12"
					},
					"parentIndex" : 1,
					"projectIndex" : 0,
					"source" : "core/Game",
					"targetIndexes" : 
					[
						1
					]
				},
				{
					"build" : "core/Logic",
					"jsonFile" : "directory-core.Logic-7f881c7205ff389b01e1.json",
					"minimumCMakeVersion" : 
					{
						"string" : "3.12"
					},
					"parentIndex" : 1,
					"projectIndex" : 0,
					"source" : "core/Logic",
					"targetIndexes" : 
					[
						3
					]
				},
				{
					"build" : "game",
					"jsonFile" : "directory-game-365c5d392ba2eb92401b.json",
					"minimumCMakeVersion" : 
					{
						"string" : "3.12"
					},
					"parentIndex" : 0,
					"projectIndex" : 0,
					"source" : "game",
					"targetIndexes" : 
					[
						0
					]
				}
			],
			"name" : "",
			"projects" : 
			[
				{
					"abstractTargetIndexes" : 
					[
						0,
						1,
						2,
						3,
						4,
						5,
						6,
						7,
						8,
						9,
						10,
						11,
						12
					],
					"directoryIndexes" : 
					[
						0,
						1,
						2,
						3,
						4,
						5,
						6,
						7
					],
					"name" : "fersa",
					"targetIndexes" : 
					[
						0,
						1,
						2,
						3,
						4
					]
				}
			],
			"targets" : 
			[
				{
					"directoryIndex" : 7,
					"id" : "fersa::@0c53ff3c4131f9152fd3",
					"jsonFile" : "target-fersa-8ca954d903c519e26a7f.json",
					"name" : "fersa",
					"projectIndex" : 0
				},
				{
					"directoryIndex" : 5,
					"id" : "game::@af0136f7f8bca7318a48",
					"jsonFile" : "target-game-ea29c62c976febcb1210.json",
					"name" : "game",
					"projectIndex" : 0
				},
				{
					"directoryIndex" : 3,
					"id" : "input::@941c823b910a1bb1ec81",
					"jsonFile" : "target-input-973f523b7dbcc3001b17.json",
					"name" : "input",
					"projectIndex" : 0
				},
				{
					"directoryIndex" : 6,
					"id" : "logic::@c4c8ae37685268088fa9",
					"jsonFile" : "target-logic-d46ffe15a9360af7eaec.json",
					"name" : "logic",
					"projectIndex" : 0
				},
				{
					"directoryIndex" : 2,
					"id" : "window::@0bf90d74aef8db95f6b7",
					"jsonFile" : "target-window-615ea19d42c861073959.json",
					"name" : "window",
					"projectIndex" : 0
				}
			]
		}
	],
	"kind" : "codemodel",
	"paths" : 
	{
		"build" : "/home/nubsdre/Documents/codes/projects/game_engine/build",
		"source" : "/home/nubsdre/Documents/codes/projects/game_engine"
	},
	"version" : 
	{
		"major" : 2,
		"minor" : 9
	}
}
