{
	"archive" : {},
	"artifacts" : 
	[
		{
			"path" : "core/Game/libgame.a"
		}
	],
	"backtrace" : 1,
	"backtraceGraph" : 
	{
		"commands" : 
		[
			"add_library",
			"target_link_libraries"
		],
		"files" : 
		[
			"core/Game/CMakeLists.txt"
		],
		"nodes" : 
		[
			{
				"file" : 0
			},
			{
				"command" : 0,
				"file" : 0,
				"line" : 1,
				"parent" : 0
			},
			{
				"command" : 1,
				"file" : 0,
				"line" : 6,
				"parent" : 0
			}
		]
	},
	"codemodelVersion" : 
	{
		"major" : 2,
		"minor" : 9
	},
	"compileDependencies" : 
	[
		{
			"backtrace" : 2,
			"id" : "graphics::@f77c298895aae6dc9943"
		}
	],
	"compileGroups" : 
	[
		{
			"compileCommandFragments" : 
			[
				{
					"fragment" : "-std=gnu++20"
				}
			],
			"language" : "CXX",
			"languageStandard" : 
			{
				"backtraces" : 
				[
					1
				],
				"standard" : "20"
			},
			"sourceIndexes" : 
			[
				0
			]
		}
	],
	"id" : "game::@af0136f7f8bca7318a48",
	"interfaceLinkLibraries" : 
	[
		{
			"backtrace" : 2,
			"id" : "graphics::@f77c298895aae6dc9943"
		}
	],
	"linkLibraries" : 
	[
		{
			"backtrace" : 2,
			"id" : "graphics::@f77c298895aae6dc9943"
		}
	],
	"name" : "game",
	"nameOnDisk" : "libgame.a",
	"paths" : 
	{
		"build" : "core/Game",
		"source" : "core/Game"
	},
	"sourceGroups" : 
	[
		{
			"name" : "Source Files",
			"sourceIndexes" : 
			[
				0
			]
		},
		{
			"name" : "Header Files",
			"sourceIndexes" : 
			[
				1
			]
		}
	],
	"sources" : 
	[
		{
			"backtrace" : 1,
			"compileGroupIndex" : 0,
			"path" : "core/Game/Game.cpp",
			"sourceGroupIndex" : 0
		},
		{
			"backtrace" : 1,
			"path" : "core/Game/Game.hpp",
			"sourceGroupIndex" : 1
		}
	],
	"type" : "STATIC_LIBRARY"
}
